seigr_toolset_transmissions/__init__.py
seigr_toolset_transmissions/chamber/__init__.py
seigr_toolset_transmissions/chamber/chamber.py
seigr_toolset_transmissions/core/__init__.py
seigr_toolset_transmissions/core/node.py
seigr_toolset_transmissions/core/transport.py
seigr_toolset_transmissions/crypto/__init__.py
seigr_toolset_transmissions/crypto/context.py
seigr_toolset_transmissions/crypto/node_identity.py
seigr_toolset_transmissions/crypto/session_keys.py
seigr_toolset_transmissions/crypto/stc_wrapper.py
seigr_toolset_transmissions/crypto/streaming.py
seigr_toolset_transmissions/endpoints/__init__.py
seigr_toolset_transmissions/endpoints/manager.py
seigr_toolset_transmissions/events/__init__.py
seigr_toolset_transmissions/events/emitter.py
seigr_toolset_transmissions/frame/__init__.py
seigr_toolset_transmissions/frame/frame.py
seigr_toolset_transmissions/handshake/__init__.py
seigr_toolset_transmissions/handshake/handshake.py
seigr_toolset_transmissions/nat/__init__.py
seigr_toolset_transmissions/nat/coordinator.py
seigr_toolset_transmissions/nat/manual.py
seigr_toolset_transmissions/nat/relay.py
seigr_toolset_transmissions/nat/relay_server.py
seigr_toolset_transmissions/session/__init__.py
seigr_toolset_transmissions/session/continuity.py
seigr_toolset_transmissions/session/session.py
seigr_toolset_transmissions/session/session_manager.py
seigr_toolset_transmissions/storage/__init__.py
seigr_toolset_transmissions/storage/binary_storage.py
seigr_toolset_transmissions/storage/provider.py
seigr_toolset_transmissions/stream/__init__.py
seigr_toolset_transmissions/stream/probabilistic_stream.py
seigr_toolset_transmissions/stream/stream.py
seigr_toolset_transmissions/stream/stream_manager.py
seigr_toolset_transmissions/streaming/__init__.py
seigr_toolset_transmissions/streaming/decoder.py
seigr_toolset_transmissions/streaming/encoder.py
seigr_toolset_transmissions/transport/__init__.py
seigr_toolset_transmissions/transport/udp.py
seigr_toolset_transmissions-0.2.0a0.dist-info/licenses/LICENSE
seigr_toolset_transmissions-0.2.0a0.dist-info/METADATA
seigr_toolset_transmissions-0.2.0a0.dist-info/WHEEL
seigr_toolset_transmissions-0.2.0a0.dist-info/entry_points.txt
seigr_toolset_transmissions-0.2.0a0.dist-info/top_level.txt
seigr_toolset_transmissions-0.2.0a0.dist-info/RECORD
