Metadata-Version: 2.4
Name: seigr-toolset-transmissions
Version: 0.2.0a0
Summary: Self-sovereign P2P streaming protocol with pure STC cryptography (Pre-release Alpha)
Author-email: Sergi Saldaña-Massó - Seigr Lab <sergism@gmail.com>
License-Expression: MIT
Keywords: seigr,encryption,networking,protocol,binary,transmission
Classifier: Development Status :: 3 - Alpha
Classifier: Intended Audience :: Developers
Classifier: Topic :: System :: Networking
Classifier: Topic :: Security :: Cryptography
Classifier: Programming Language :: Python :: 3
Requires-Python: >=3.9
License-File: LICENSE
Requires-Dist: seigr-toolset-crypto>=0.4.0
Provides-Extra: dev
Requires-Dist: pytest>=7.0.0; extra == "dev"
Requires-Dist: pytest-asyncio>=0.21.0; extra == "dev"
Requires-Dist: pytest-cov>=4.0.0; extra == "dev"
Requires-Dist: ruff>=0.1.0; extra == "dev"
Requires-Dist: mypy>=1.0.0; extra == "dev"
Provides-Extra: websocket
Requires-Dist: websockets>=11.0.0; extra == "websocket"
Dynamic: license-file
